{
  "Covid-19": [
    "covin",
    "covid",
    "coven 19",
    "coven",
    "kobit",
    "kova 19",
    "Kova",
    "covenanting",
    "Cova da 19",
    "Cova",
    "coveted",
    "covid19",
    "covet 19",
    "covet"
  ],
  "capital": [
    "epa",
    "cdc",
    "nycha",
    "nyc",
    "osha",
    "usa",
    "nypd",
    "doe",
    "dob",
    "dot",
    "dca",
    "ppe",
    "cecm",
    "sapo",
    "edc",
    "rfp",
    "d-o-t",
    "wpa",
    "dcla",
    "cd",
    "dpla",
    "boe"
  ],
  "title": [
    "brooklyn",
    "manhattan",
    "queens",
    "bronx",
    "staten island",
    "new york city",
    "lexington",
    "rikers",
    "florida",
    "california",
    "january",
    "cuomo",
    "blasio",
    "palitz",
    "america",
    "pacific",
    "june",
    "district needs"
  ],
  "filler": [
    "um",
    "uh",
    "[music]",
    "[Music]"
  ],
  "spelling": {
    "screenway":"greenway",
    "We can go to the next slide": "",
    "adc": "edc",
    "9, 11": "9/11",
    "conned": "Con Edison",
    "mirrors": "minors"
  }
}